CHANGELOG
MANIFEST.in
README.md
setup.py
soda/__init__.py
soda/deploy/__init__.py
soda/deploy/deps.py
soda/deploy/django.py
soda/deploy/git.py
soda/deploy/opbeat.py
soda/deploy/options.py
soda/deploy/supervisor.py
soda/fabric/__init__.py
soda/fabric/base.py
soda/host/__init__.py
soda/host/nginx.py
soda/host/ssl.py
soda/misc/__init__.py
soda/misc/display.py
soda/misc/main.py
soda_pylib.egg-info/PKG-INFO
soda_pylib.egg-info/SOURCES.txt
soda_pylib.egg-info/dependency_links.txt
soda_pylib.egg-info/requires.txt
soda_pylib.egg-info/top_level.txt