Metadata-Version: 1.1
Name: soda-pylib
Version: 1.3.5
Summary: Utilities to help projets at SODA Virtual.
Home-page: https://gitlab.com/sodavirtual/soda-pylib
Author: Evandro Myller
Author-email: emyller@7ws.co
License: MIT
Keywords: deploy fabric
Platform: UNKNOWN
Classifier: Development Status :: 3 - Alpha
Classifier: Intended Audience :: Developers
Classifier: Topic :: Software Development :: Build Tools
Classifier: License :: OSI Approved :: MIT License
Classifier: Programming Language :: Python :: 2
Classifier: Programming Language :: Python :: 2.7
Classifier: Programming Language :: Python :: 3.5
Classifier: Programming Language :: Python :: 3.6
